apis/__init__.py
apis/apis.py
apis/ctecs_check_demand_in_region_v41_api.py
apis/ctecs_create_instance_v41_api.py
apis/ctecs_create_keypair_v41_api.py
apis/ctecs_delete_instance_and_related_resource_api.py
apis/ctecs_delete_keypair_v41_api.py
apis/ctecs_describe_instances_api.py
apis/ctecs_destroy_instance_api.py
apis/ctecs_details_keypair_v41_api.py
apis/ctecs_get_ecs_flavors_api.py
apis/ctecs_import_keypair_v41_api.py
apis/ctecs_instance_detach_keypair_v41_api.py
apis/ctecs_keypair_attach_instance_v41_api.py
apis/ctecs_list_regions_v41_api.py
apis/ctecs_query_customer_quotas_in_region_v41_api.py
apis/ctecs_query_customer_resources_in_region_v41_api.py
apis/ctecs_query_instance_statistics_v41_api.py
apis/ctecs_query_job_info_v41_api.py
apis/ctecs_query_new_order_price_v41_api.py
apis/ctecs_query_new_order_price_v42_api.py
apis/ctecs_query_order_uuid_v41_api.py
apis/ctecs_query_products_in_region_v41_api.py
apis/ctecs_query_renew_order_price_v41_api.py
apis/ctecs_query_renew_order_price_v42_api.py
apis/ctecs_query_summary_in_region_v41_api.py
apis/ctecs_query_upgrade_order_price_v41_api.py
apis/ctecs_query_upgrade_order_price_v42_api.py
apis/ctecs_query_zones_in_region_v41_api.py
apis/ctecs_reboot_instance_v41_api.py
apis/ctecs_rebuild_instance_v41_api.py
apis/ctecs_reset_instance_password_v41_api.py
apis/ctecs_resubscribe_instance_v41_api.py
apis/ctecs_start_instance_v41_api.py
apis/ctecs_stop_instance_v41_api.py
apis/ctecs_update_ecs_label_v41_api.py
apis/ctecs_update_flavor_spec_v41_api.py
apis/ctecs_update_instance_v41_api.py
apis/ctecs_update_keypair_v41_api.py
core/__init__.py
core/client.py
core/credential.py
core/ctapi_sdk_python.py
core/exception.py
core/http_methods.py
core/request.py
core/request_builder.py
core/request_template.py
core/signer.py
core/utils.py
ctyunsdk_ecs20220909/__init__.py
ctyunsdk_ecs20220909/apis/__init__.py
ctyunsdk_ecs20220909/apis/apis.py
ctyunsdk_ecs20220909/apis/ctecs_check_demand_in_region_v41_api.py
ctyunsdk_ecs20220909-2.0.0.dist-info/LICENSE.txt
ctyunsdk_ecs20220909-2.0.0.dist-info/METADATA
ctyunsdk_ecs20220909-2.0.0.dist-info/WHEEL
ctyunsdk_ecs20220909-2.0.0.dist-info/top_level.txt
ctyunsdk_ecs20220909-2.0.0.dist-info/RECORD
