Metadata-Version: 2.1
Name: ctyunsdk-ecs20220909
Version: 2.0.0
Summary: UNKNOWN
Home-page: https://github.com/ctyunsdk/ctyun-python-sdk
Author: Ctyun Cloud SDK
Author-email: ctyunsdk@chinatelecom.cn
License: LICENSE.txt
Project-URL: Source, https://github.com/ctyunsdk/ctyun-python-sdk
Platform: UNKNOWN
Requires-Python: >=3.9
Requires-Dist: requests>=2.32.4
